<?xml version="1.0" encoding="UTF-8"?>
<!DOCTYPE mapper PUBLIC "-//mybatis.org//DTD Mapper 3.0//EN" "http://mybatis.org/dtd/mybatis-3-mapper.dtd">
<mapper namespace="cn.bnsr.edu_yun.frontstage.train.mapper.ClassifyRelationMapper">
  <resultMap id="BaseResultMap" type="cn.bnsr.edu_yun.frontstage.train.po.ClassifyRelation">
    <!--
      WARNING - @mbggenerated
      This element is automatically generated by MyBatis Generator, do not modify.
      This element was generated on Thu May 18 15:47:28 CST 2017.
    -->
    <id column="id" jdbcType="BIGINT" property="id" />
    <result column="name" jdbcType="VARCHAR" property="name" />
    <result column="code" jdbcType="INTEGER" property="code" />
    <result column="remarks" jdbcType="VARCHAR" property="remarks" />
    <result column="parent_id" jdbcType="BIGINT" property="parent_id" />
    <result column="create_time" jdbcType="TIMESTAMP" property="create_time" />
    <result column="type" jdbcType="INTEGER" property="type" />
    <result column="source_type" jdbcType="INTEGER" property="source_type" />
    <result column="source_id" jdbcType="BIGINT" property="source_id" />
  </resultMap>
  <sql id="Base_Column_List">
    <!--
      WARNING - @mbggenerated
      This element is automatically generated by MyBatis Generator, do not modify.
      This element was generated on Thu May 18 15:47:28 CST 2017.
    -->
    id, name, code, remarks, parent_id, create_time, type, source_type, source_id
  </sql>
  <select id="selectByPrimaryKey" parameterType="java.lang.Long" resultMap="BaseResultMap">
    <!--
      WARNING - @mbggenerated
      This element is automatically generated by MyBatis Generator, do not modify.
      This element was generated on Thu May 18 15:47:28 CST 2017.
    -->
    select 
    <include refid="Base_Column_List" />
    from classify_relation
    where id = #{id,jdbcType=BIGINT}
  </select>
  <delete id="deleteByPrimaryKey" parameterType="java.lang.Long">
    <!--
      WARNING - @mbggenerated
      This element is automatically generated by MyBatis Generator, do not modify.
      This element was generated on Thu May 18 15:47:28 CST 2017.
    -->
    delete from classify_relation
    where id = #{id,jdbcType=BIGINT}
  </delete>
  <insert id="insert" parameterType="cn.bnsr.edu_yun.frontstage.train.po.ClassifyRelation">
    <!--
      WARNING - @mbggenerated
      This element is automatically generated by MyBatis Generator, do not modify.
      This element was generated on Thu May 18 15:47:28 CST 2017.
    -->
    <selectKey keyProperty="id" order="AFTER" resultType="java.lang.Long">
      SELECT LAST_INSERT_ID()
    </selectKey>
    insert into classify_relation (name, code, remarks, 
      parent_id, create_time, type, 
      source_type, source_id)
    values (#{name,jdbcType=VARCHAR}, #{code,jdbcType=INTEGER}, #{remarks,jdbcType=VARCHAR}, 
      #{parent_id,jdbcType=BIGINT}, #{create_time,jdbcType=TIMESTAMP}, #{type,jdbcType=INTEGER}, 
      #{source_type,jdbcType=INTEGER}, #{source_id,jdbcType=BIGINT})
  </insert>
  <insert id="insertSelective" parameterType="cn.bnsr.edu_yun.frontstage.train.po.ClassifyRelation">
    <!--
      WARNING - @mbggenerated
      This element is automatically generated by MyBatis Generator, do not modify.
      This element was generated on Thu May 18 15:47:28 CST 2017.
    -->
    <selectKey keyProperty="id" order="AFTER" resultType="java.lang.Long">
      SELECT LAST_INSERT_ID()
    </selectKey>
    insert into classify_relation
    <trim prefix="(" suffix=")" suffixOverrides=",">
      <if test="name != null">
        name,
      </if>
      <if test="code != null">
        code,
      </if>
      <if test="remarks != null">
        remarks,
      </if>
      <if test="parent_id != null">
        parent_id,
      </if>
      <if test="create_time != null">
        create_time,
      </if>
      <if test="type != null">
        type,
      </if>
      <if test="source_type != null">
        source_type,
      </if>
      <if test="source_id != null">
        source_id,
      </if>
    </trim>
    <trim prefix="values (" suffix=")" suffixOverrides=",">
      <if test="name != null">
        #{name,jdbcType=VARCHAR},
      </if>
      <if test="code != null">
        #{code,jdbcType=INTEGER},
      </if>
      <if test="remarks != null">
        #{remarks,jdbcType=VARCHAR},
      </if>
      <if test="parent_id != null">
        #{parent_id,jdbcType=BIGINT},
      </if>
      <if test="create_time != null">
        #{create_time,jdbcType=TIMESTAMP},
      </if>
      <if test="type != null">
        #{type,jdbcType=INTEGER},
      </if>
      <if test="source_type != null">
        #{source_type,jdbcType=INTEGER},
      </if>
      <if test="source_id != null">
        #{source_id,jdbcType=BIGINT},
      </if>
    </trim>
  </insert>
  <update id="updateByPrimaryKeySelective" parameterType="cn.bnsr.edu_yun.frontstage.train.po.ClassifyRelation">
    <!--
      WARNING - @mbggenerated
      This element is automatically generated by MyBatis Generator, do not modify.
      This element was generated on Thu May 18 15:47:28 CST 2017.
    -->
    update classify_relation
    <set>
      <if test="name != null">
        name = #{name,jdbcType=VARCHAR},
      </if>
      <if test="code != null">
        code = #{code,jdbcType=INTEGER},
      </if>
      <if test="remarks != null">
        remarks = #{remarks,jdbcType=VARCHAR},
      </if>
      <if test="parent_id != null">
        parent_id = #{parent_id,jdbcType=BIGINT},
      </if>
      <if test="create_time != null">
        create_time = #{create_time,jdbcType=TIMESTAMP},
      </if>
      <if test="type != null">
        type = #{type,jdbcType=INTEGER},
      </if>
      <if test="source_type != null">
        source_type = #{source_type,jdbcType=INTEGER},
      </if>
      <if test="source_id != null">
        source_id = #{source_id,jdbcType=BIGINT},
      </if>
    </set>
    where id = #{id,jdbcType=BIGINT}
  </update>
  <update id="updateByPrimaryKey" parameterType="cn.bnsr.edu_yun.frontstage.train.po.ClassifyRelation">
    <!--
      WARNING - @mbggenerated
      This element is automatically generated by MyBatis Generator, do not modify.
      This element was generated on Thu May 18 15:47:28 CST 2017.
    -->
    update classify_relation
    set name = #{name,jdbcType=VARCHAR},
      code = #{code,jdbcType=INTEGER},
      remarks = #{remarks,jdbcType=VARCHAR},
      parent_id = #{parent_id,jdbcType=BIGINT},
      create_time = #{create_time,jdbcType=TIMESTAMP},
      type = #{type,jdbcType=INTEGER},
      source_type = #{source_type,jdbcType=INTEGER},
      source_id = #{source_id,jdbcType=BIGINT}
    where id = #{id,jdbcType=BIGINT}
  </update>
  
  <select id="queryAllBaseClassify" parameterType="cn.bnsr.edu_yun.frontstage.train.view.ClassifyRelationView" resultType="cn.bnsr.edu_yun.frontstage.train.view.ClassifyRelationView">
  	SELECT id, name, code FROM classify_relation 
	WHERE type = ${type} AND source_type = ${source_type} 
	AND source_id = ${source_id} 
	<if test="parent_id == null">
	AND parent_id IS NULL
	</if>
	ORDER BY code
	<if test="rows>0">
  		LIMIT ${startLine},${rows}
  	</if>
  </select>
  
  <select id="getSonClassifys" parameterType="java.lang.Long" resultType="cn.bnsr.edu_yun.frontstage.train.po.ClassifyRelation">
  	SELECT id, name, code, parent_id FROM classify_relation 
	WHERE parent_id = ${parent_id}
	ORDER BY code
  </select>
  
  <select id="queryCLassifysByPid" resultType="cn.bnsr.edu_yun.frontstage.train.po.ClassifyRelation">
  	SELECT id,name,parent_id FROM classify_relation where type=#{type} AND source_type = #{source_type} 
  	 <choose>
  	 	<when test="parent_id!=null">
  	 		AND parent_id = #{parent_id}
  	 	</when>
  	 	<otherwise>
  	 		AND parent_id is null
  	 	</otherwise>
  	 </choose>
  </select>
  
  <select id="countBaseClassifyRelation" parameterType="cn.bnsr.edu_yun.frontstage.train.view.ClassifyRelationView" resultType="java.lang.Integer">
  	SELECT COUNT(*) FROM classify_relation 
	WHERE type = ${type} AND source_type = ${source_type} 
	AND source_id = ${source_id} 
	<if test="parent_id == null">
	AND parent_id IS NULL
	</if>
  </select>
  
  <select id="getMaxSeq" parameterType="cn.bnsr.edu_yun.frontstage.train.view.ClassifyRelationView" resultType="java.lang.Integer">
  	SELECT MAX(code) FROM classify_relation 
	WHERE source_type = ${source_type} 
	AND source_id = ${source_id} 
	<if test="parent_id != null">
	AND parent_id = ${parent_id} 
	</if>
  </select>
  
</mapper>