<?xml version="1.0" encoding="UTF-8" ?>
<!DOCTYPE mapper PUBLIC "-//mybatis.org//DTD Mapper 3.0//EN" "http://mybatis.org/dtd/mybatis-3-mapper.dtd" >
<mapper namespace="cn.bnsr.edu_yun.frontstage.train.mapper.MessageFileMapper" >
  <resultMap id="BaseResultMap" type="cn.bnsr.edu_yun.frontstage.train.po.MessageFile" >
    <!--
      WARNING - @mbggenerated
      This element is automatically generated by MyBatis Generator, do not modify.
      This element was generated on Fri May 12 15:21:17 CST 2017.
    -->
    <id column="id" property="id" jdbcType="BIGINT" />
    <result column="path" property="path" jdbcType="VARCHAR" />
    <result column="message_id" property="message_id" jdbcType="BIGINT" />
    <result column="file_name" property="file_name" jdbcType="VARCHAR" />
  </resultMap>
  <sql id="Base_Column_List" >
    <!--
      WARNING - @mbggenerated
      This element is automatically generated by MyBatis Generator, do not modify.
      This element was generated on Fri May 12 15:21:17 CST 2017.
    -->
    id, path, message_id,file_name
  </sql>
  <select id="selectByPrimaryKey" resultMap="BaseResultMap" parameterType="java.lang.Long" >
    <!--
      WARNING - @mbggenerated
      This element is automatically generated by MyBatis Generator, do not modify.
      This element was generated on Fri May 12 15:21:17 CST 2017.
    -->
    select 
    <include refid="Base_Column_List" />
    from message_file
    where id = #{id,jdbcType=BIGINT}
  </select>
  <delete id="deleteByPrimaryKey" parameterType="java.lang.Long" >
    <!--
      WARNING - @mbggenerated
      This element is automatically generated by MyBatis Generator, do not modify.
      This element was generated on Fri May 12 15:21:17 CST 2017.
    -->
    delete from message_file
    where id = #{id,jdbcType=BIGINT}
  </delete>
  <delete id="deleteByMessageId" parameterType="java.lang.Long" >
    delete from message_file
    where message_id = #{id,jdbcType=BIGINT}
  </delete>
  <insert id="insert" parameterType="cn.bnsr.edu_yun.frontstage.train.po.MessageFile" >
    <!--
      WARNING - @mbggenerated
      This element is automatically generated by MyBatis Generator, do not modify.
      This element was generated on Fri May 12 15:21:17 CST 2017.
    -->
    <selectKey resultType="java.lang.Long" keyProperty="id" order="AFTER" >
      SELECT LAST_INSERT_ID()
    </selectKey>
    insert into message_file (path, message_id,file_name)
    values (#{path,jdbcType=VARCHAR}, #{message_id,jdbcType=BIGINT},#{file_name,jdbcType=VARCHAR})
  </insert>
  <insert id="insertSelective" parameterType="cn.bnsr.edu_yun.frontstage.train.po.MessageFile" >
    <!--
      WARNING - @mbggenerated
      This element is automatically generated by MyBatis Generator, do not modify.
      This element was generated on Fri May 12 15:21:17 CST 2017.
    -->
    <selectKey resultType="java.lang.Long" keyProperty="id" order="AFTER" >
      SELECT LAST_INSERT_ID()
    </selectKey>
    insert into message_file
    <trim prefix="(" suffix=")" suffixOverrides="," >
      <if test="path != null" >
        path,
      </if>
      <if test="message_id != null" >
        message_id,
      </if>
      <if test="file_name != null" >
        file_name,
      </if>
    </trim>
    <trim prefix="values (" suffix=")" suffixOverrides="," >
      <if test="path != null" >
        #{path,jdbcType=VARCHAR},
      </if>
      <if test="message_id != null" >
        #{message_id,jdbcType=BIGINT},
      </if>
      <if test="file_name != null" >
        #{file_name,jdbcType=VARCHAR},
      </if>
    </trim>
  </insert>
  <update id="updateByPrimaryKeySelective" parameterType="cn.bnsr.edu_yun.frontstage.train.po.MessageFile" >
    <!--
      WARNING - @mbggenerated
      This element is automatically generated by MyBatis Generator, do not modify.
      This element was generated on Fri May 12 15:21:17 CST 2017.
    -->
    update message_file
    <set >
      <if test="path != null" >
        path = #{path,jdbcType=VARCHAR},
      </if>
      <if test="message_id != null" >
        message_id = #{message_id,jdbcType=BIGINT},
      </if>
      <if test="file_name != null" >
        file_name = #{file_name,jdbcType=VARCHAR},
      </if>
      
    </set>
    where id = #{id,jdbcType=BIGINT}
  </update>
  <update id="updateByPrimaryKey" parameterType="cn.bnsr.edu_yun.frontstage.train.po.MessageFile" >
    <!--
      WARNING - @mbggenerated
      This element is automatically generated by MyBatis Generator, do not modify.
      This element was generated on Fri May 12 15:21:17 CST 2017.
    -->
    update message_file
    set path = #{path,jdbcType=VARCHAR},
      message_id = #{message_id,jdbcType=BIGINT},
      file_name = #{file_name,jdbcType=VARCHAR}
    where id = #{id,jdbcType=BIGINT}
  </update>
</mapper>